font_unicode-0.9.2.dist-info/DESCRIPTION.rst
font_unicode-0.9.2.dist-info/METADATA
font_unicode-0.9.2.dist-info/RECORD
font_unicode-0.9.2.dist-info/WHEEL
font_unicode-0.9.2.dist-info/entry_points.txt
font_unicode-0.9.2.dist-info/metadata.json
font_unicode-0.9.2.dist-info/top_level.txt
fontunicode/__init__.py
fontunicode/app.py
fontunicode/settings.py
fontunicode/commands/__init__.py
fontunicode/commands/search.py
fontunicode/glyphlist/NOTICE.txt
fontunicode/glyphlist/NamesList.txt
fontunicode/glyphlist/__init__.py
fontunicode/glyphlist/aglfn.txt
fontunicode/glyphlist/db-generator.py
fontunicode/glyphlist/unicode.db
