Metadata-Version: 1.1
Name: font-unicode
Version: 0.9.2
Summary: Command line Unicode character code point and character name search
Home-page: https://github.com/source-foundry/font-unicode
Author: Christopher Simpkins
Author-email: chris@sourcefoundry.org
License: MIT license
Keywords: unicode,font,fonts,typeface,typefaces,type,type design,type development,character,code point,name,search
Platform: any
Classifier: Intended Audience :: End Users/Desktop
Classifier: Development Status :: 4 - Beta
Classifier: Natural Language :: English
Classifier: License :: OSI Approved :: MIT License
Classifier: Programming Language :: Python
Classifier: Programming Language :: Python :: 2
Classifier: Programming Language :: Python :: 3
Classifier: Operating System :: MacOS :: MacOS X
Classifier: Operating System :: POSIX
Classifier: Operating System :: Unix
Classifier: Operating System :: Microsoft :: Windows
